scripro/Ori_data.py
scripro/__init__.py
scripro/cli.py
scripro/supercell.py
scripro/utils.py
scripro/data/bedGraphToBigWig
scripro/data/hg38.genome
scripro/data/mm10.genome
scripro-1.1.30.dist-info/METADATA
scripro-1.1.30.dist-info/WHEEL
scripro-1.1.30.dist-info/entry_points.txt
scripro-1.1.30.dist-info/top_level.txt
scripro-1.1.30.dist-info/RECORD
