Metadata-Version: 2.1
Name: scripro
Version: 1.1.30
Summary: Single-cell gene regulation network inference by large-scale data integration Pro
Home-page: https://github.com/xuyunfan9991/SCRIPro
Author: Xu Yunfan
Author-email: xuyunfan9991@gmail.com
License: GPL-3.0+
Keywords: Single-Cell Gene Regulatory Network Inference using ChIP-seq for Multi-omics
Classifier: Programming Language :: Python :: 3
Classifier: License :: OSI Approved :: GNU General Public License v3 or later (GPLv3+)
Classifier: Operating System :: OS Independent
Requires-Python: >=3.8
Requires-Dist: anndata ==0.9.2
Requires-Dist: h5py ==3.7.0
Requires-Dist: matplotlib ==3.7.1
Requires-Dist: numpy ==1.22.3
Requires-Dist: pandas ==2.0.3
Requires-Dist: scanpy ==1.9.5
Requires-Dist: scipy ==1.9.1
Requires-Dist: seaborn ==0.12.2
Requires-Dist: scglue ==0.3.2
Requires-Dist: lisa2[coverage]
Requires-Dist: tables
Requires-Dist: tqdm
Requires-Dist: ipywidgets
